kousuan/__init__.py
kousuan/cli.py
kousuan/core.py
kousuan/base/engine.py
kousuan/fraction/base_types.py
kousuan/fraction/doc.md
kousuan/fraction/engine.py
kousuan/fraction/fraction-questions.md
kousuan/fraction/list.md
kousuan/fraction/parser.py
kousuan/fraction/registry.py
kousuan/fraction/calculators/cross_multiply_compare.py
kousuan/fraction/calculators/decimal_to_fraction.py
kousuan/fraction/calculators/different_denominator_add.py
kousuan/fraction/calculators/different_denominator_subtract.py
kousuan/fraction/calculators/expression_compare.py
kousuan/fraction/calculators/fraction_compare.py
kousuan/fraction/calculators/fraction_convert.py
kousuan/fraction/calculators/fraction_divide.py
kousuan/fraction/calculators/fraction_integer_multiply.py
kousuan/fraction/calculators/fraction_multiply.py
kousuan/fraction/calculators/fraction_to_decimal.py
kousuan/fraction/calculators/integer_fraction_compare.py
kousuan/fraction/calculators/mixed_improper_convert.py
kousuan/fraction/calculators/ratio_equation.py
kousuan/fraction/calculators/ratio_to_fraction.py
kousuan/fraction/calculators/ratio_to_value.py
kousuan/fraction/calculators/reciprocal.py
kousuan/fraction/calculators/reciprocal_equation.py
kousuan/fraction/calculators/reduce_fraction.py
kousuan/fraction/calculators/same_denominator_add.py
kousuan/fraction/calculators/same_denominator_subtract.py
kousuan/fraction/calculators/same_numerator_compare.py
kousuan/mixed/__init__.py
kousuan/mixed/base_types.py
kousuan/mixed/doc.md
kousuan/mixed/engine.py
kousuan/mixed/parser.py
kousuan/mixed/registry.py
kousuan/mixed/calculators/__init__.py
kousuan/mixed/calculators/add_sub_left_to_right.py
kousuan/mixed/calculators/bracketed_mix_evaluator.py
kousuan/mixed/calculators/complement_rewriting.py
kousuan/mixed/calculators/distribution_optimizer.py
kousuan/mixed/calculators/mul_div_left_to_right.py
kousuan/mixed/calculators/parentheses_evaluator.py
kousuan/mixed/calculators/standard_order_evaluator.py
kousuan-0.1.3.dist-info/METADATA
kousuan-0.1.3.dist-info/WHEEL
kousuan-0.1.3.dist-info/entry_points.txt
kousuan-0.1.3.dist-info/top_level.txt
kousuan-0.1.3.dist-info/RECORD
