Metadata-Version: 2.4
Name: kousuan
Version: 0.1.3
Summary: A Python package for providing mental arithmetic calculation skills
Author-email: liandong <linkwisdom@gmail.com>
License: MIT
Project-URL: Homepage, https://github.com/liuliandong/kousuan
Project-URL: Bug Reports, https://github.com/liuliandong/kousuan/issues
Project-URL: Source, https://github.com/liuliandong/kousuan
Keywords: math,mental-arithmetic,calculation,education,kousuan
Classifier: Development Status :: 3 - Alpha
Classifier: Intended Audience :: Education
Classifier: License :: OSI Approved :: MIT License
Classifier: Operating System :: OS Independent
Classifier: Programming Language :: Python :: 3
Classifier: Programming Language :: Python :: 3.7
Classifier: Programming Language :: Python :: 3.8
Classifier: Programming Language :: Python :: 3.9
Classifier: Programming Language :: Python :: 3.10
Classifier: Programming Language :: Python :: 3.11
Classifier: Topic :: Education
Classifier: Topic :: Scientific/Engineering :: Mathematics
Requires-Python: >=3.7
Provides-Extra: dev
Requires-Dist: pytest>=6.0; extra == "dev"
Requires-Dist: pytest-cov; extra == "dev"
Requires-Dist: black; extra == "dev"
Requires-Dist: flake8; extra == "dev"
